nextcordhealthcheck/__init__.py
nextcordhealthcheck/__main__.py
nextcordhealthcheck/core.py
nextcordhealthcheck-0.1.3.dist-info/LICENSE
nextcordhealthcheck-0.1.3.dist-info/METADATA
nextcordhealthcheck-0.1.3.dist-info/WHEEL
nextcordhealthcheck-0.1.3.dist-info/entry_points.txt
nextcordhealthcheck-0.1.3.dist-info/top_level.txt
nextcordhealthcheck-0.1.3.dist-info/RECORD
