Metadata-Version: 2.1
Name: nextcordhealthcheck
Version: 0.1.3
Summary: A small Python 3 library and command line app to automate Docker health checks for nextcord bots.
Home-page: https://github.com/I-dan-mi-I/NextcordHealthCheck
Keywords: nextcord docker healthcheck health check bot
Classifier: Intended Audience :: Developers
Classifier: License :: OSI Approved :: MIT License
Classifier: Programming Language :: Python :: 3
License-File: LICENSE
Requires-Dist: nextcord
